embedx/__init__.py
embedx/embedx.py
embedx/version.py
embedx-0.0.7.dist-info/DESCRIPTION.rst
embedx-0.0.7.dist-info/METADATA
embedx-0.0.7.dist-info/RECORD
embedx-0.0.7.dist-info/WHEEL
embedx-0.0.7.dist-info/metadata.json
embedx-0.0.7.dist-info/top_level.txt
