Metadata-Version: 2.0
Name: embedx
Version: 0.0.7
Summary: Generate responsive, embeddable HTML/JS code from URL of online content
Home-page: https://github.com/kmonsoor/embedX
Author: Khaled Monsoor
Author-email: k@kmonsoor.com
License: MIT
Keywords: embed,html,javascript,embeddable,code generation,from url
Platform: any
Classifier: Development Status :: 3 - Alpha
Classifier: Programming Language :: Python :: 2
Classifier: Programming Language :: Python :: 3
Classifier: Environment :: Console
Classifier: Environment :: Web Environment
Classifier: Intended Audience :: Developers
Classifier: Operating System :: OS Independent
Classifier: License :: OSI Approved :: MIT License
Classifier: Topic :: Utilities
Classifier: Topic :: Software Development :: Libraries :: Python Modules
